bitmask_repos.py
bitmask_repos-1.0.dist-info/DESCRIPTION.rst
bitmask_repos-1.0.dist-info/METADATA
bitmask_repos-1.0.dist-info/RECORD
bitmask_repos-1.0.dist-info/WHEEL
bitmask_repos-1.0.dist-info/entry_points.txt
bitmask_repos-1.0.dist-info/metadata.json
bitmask_repos-1.0.dist-info/top_level.txt
