Metadata-Version: 2.0
Name: bitmask-repos
Version: 1.0
Summary: setup bitmask debian repositories
Home-page: https://bitmask.net
Author: Kali Kaneko
Author-email: kali@leap.se
License: UNKNOWN
Platform: UNKNOWN
